tigs/__init__.py
tigs/chat_providers.py
tigs/cli.py
tigs/notes_merger.py
tigs/storage.py
tigs/tui/__init__.py
tigs/tui/chat_view.py
tigs/tui/color_constants.py
tigs/tui/commit_details_view.py
tigs/tui/commits_view.py
tigs/tui/indicators.py
tigs/tui/layout_manager.py
tigs/tui/logs_view.py
tigs/tui/messages_view.py
tigs/tui/pane_renderer.py
tigs/tui/protocols.py
tigs/tui/scrollable_mixin.py
tigs/tui/selection_mixin.py
tigs/tui/store_app.py
tigs/tui/text_utils.py
tigs/tui/view_app.py
tigs/tui/view_scroll_mixin.py
tigs-0.1.4.dist-info/METADATA
tigs-0.1.4.dist-info/WHEEL
tigs-0.1.4.dist-info/entry_points.txt
tigs-0.1.4.dist-info/RECORD
