Metadata-Version: 2.4
Name: tigs
Version: 0.1.4
Summary: Talks in Git → Specs - Git-based chat management system for AI-empowered software development
Project-URL: Homepage, https://github.com/sublang-ai/tigs
Project-URL: Repository, https://github.com/sublang-ai/tigs
Project-URL: Issues, https://github.com/sublang-ai/tigs/issues
Project-URL: Discord, https://discord.gg/8krkc4z5wK
Author-email: SubLang Community <hi@sublang.ai>
License: Apache-2.0
Keywords: ai,chat,chatgpt,claude,development-tools,gemini,git,llm,prompts,qwen,software-development,spec-driven,specifications,specs,version-control,vibe-coding
Classifier: Development Status :: 3 - Alpha
Classifier: Environment :: Console
Classifier: Intended Audience :: Developers
Classifier: License :: OSI Approved :: Apache Software License
Classifier: Operating System :: OS Independent
Classifier: Programming Language :: Python :: 3
Classifier: Programming Language :: Python :: 3.8
Classifier: Programming Language :: Python :: 3.9
Classifier: Programming Language :: Python :: 3.10
Classifier: Programming Language :: Python :: 3.11
Classifier: Programming Language :: Python :: 3.12
Classifier: Topic :: Software Development :: Documentation
Classifier: Topic :: Software Development :: Version Control :: Git
Requires-Python: >=3.8
Requires-Dist: click>=8.0
Requires-Dist: cligent>=0.1.6
Requires-Dist: gitpython>=3.1.30
Requires-Dist: pytest-timeout>=2.4.0
Requires-Dist: wcwidth>=0.2.13
